{
    "music_games": {
        "fnf_games":{
            "name": "Friday Night Funkin' Games",
            "description": "A collection of games based on the popular rhythm game, Friday Night Funkin'.",
            "games": [
                {
                    "title": "FNF Classic",
                    "thumbnail": "https://kbhgames.com/wp-content/uploads/2020/11/Friday-Night-Funkin.png",
                    "url": "https://fnf.kdata1.com/2024/fnf/5201/"
                },
                {
                    "title": "Friday Night Funkin VS. KAPI v2.0",
                    "thumbnail": "https://kbhgames.com/wp-content/uploads/2021/04/Friday-Night-Funkin-VS.-KAPI.jpg",
                    "url": "https://mod.fnfhub.net/games/24899?token=c28f0c6ecd0c3cc97d2a212fb9f58dd7"
                }
            ]
        },
        "rhythm_games": {
            "name": "Rhythm Games",
            "description": "A variety of rhythm-based games to test your timing and musical skills.",
            "games": [
                {
                    "title": "OSU Online",
                    "thumbnail": "https://upload.wikimedia.org/wikipedia/commons/2/29/Osu%21_logo_2024.png",
                    "url": "https://webosu-2.github.io/"
                },
                {
                    "title": "Rhythm Plus",
                    "thumbnail": "https://rhythm-plus.com/assets/logo2.png",
                    "url": "https://rhythm-plus.com/"
                },
                {
                    "title": "Geometry Dash Lite",
                    "thumbnail": "https://img.icons8.com/?size=512&id=oVj0wlZehUCr&format=png",
                    "url": "https://ozgames.io/geometry-dash/geometry-dash.embed"
                }
            ]
        }
    },
    "multiplayer_games": {
        "battle_royale": {
            "name": "Battle Royale Games",
            "description": "Engage in intense multiplayer battles where the last player standing wins.",
            "games": [
                {
                    "title": "yohoho.io",
                    "thumbnail": "https://img.poki-cdn.com/cdn-cgi/image/q=78,scq=50,width=94,height=94,fit=cover,f=auto/9b373b5219cd66a82389d81d7cda8e23/yohoho-io.jpeg",
                    "url": "https://yohoho.io/"
                },
                {
                    "title": "bruh.io",
                    "thumbnail": "https://bruh.io/logo.58fee131.png",
                    "url": "https://bruh.io/"
                }
            ]
        }
    }
}
